<?xml version="1.0" encoding="utf-8"?>
<ReferenceGroup xmlns:xsi="http://www.w3.org/2001/XMLSchema-instance" xmlns:xsd="http://www.w3.org/2001/XMLSchema" ID="6549823c-abe5-408c-801a-faaeb1c91d88" xmlns="urn:schemas-microsoft-com:xml-wcfservicemap">
  <ClientOptions>
    <GenerateAsynchronousMethods>false</GenerateAsynchronousMethods>
    <GenerateTaskBasedAsynchronousMethod>true</GenerateTaskBasedAsynchronousMethod>
    <EnableDataBinding>true</EnableDataBinding>
    <ExcludedTypes />
    <ImportXmlTypes>false</ImportXmlTypes>
    <GenerateInternalTypes>false</GenerateInternalTypes>
    <GenerateMessageContracts>false</GenerateMessageContracts>
    <NamespaceMappings />
    <CollectionMappings />
    <GenerateSerializableTypes>true</GenerateSerializableTypes>
    <Serializer>Auto</Serializer>
    <UseSerializerForFaults>true</UseSerializerForFaults>
    <ReferenceAllAssemblies>true</ReferenceAllAssemblies>
    <ReferencedAssemblies />
    <ReferencedDataContractTypes />
    <ServiceContractMappings />
  </ClientOptions>
  <MetadataSources>
    <MetadataSource Address="http://localhost:60598/Service1.svc" Protocol="http" SourceId="1" />
  </MetadataSources>
  <Metadata>
    <MetadataFile FileName="Service1.wsdl" MetadataType="Wsdl" ID="2ff9ba5e-29d8-430f-90cf-78e8eb0dacd7" SourceId="1" SourceUrl="http://localhost:60598/Service1.svc?wsdl" />
    <MetadataFile FileName="Service1.xsd" MetadataType="Schema" ID="62e17edd-7a10-47b1-84aa-10b9db820ab8" SourceId="1" SourceUrl="http://localhost:60598/Service1.svc?xsd=xsd0" />
    <MetadataFile FileName="Service1.disco" MetadataType="Disco" ID="fc9910f3-5407-4bee-8063-154fdcf1e877" SourceId="1" SourceUrl="http://localhost:60598/Service1.svc?disco" />
    <MetadataFile FileName="Service11.xsd" MetadataType="Schema" ID="20794176-51a0-4188-94a5-6184909e886e" SourceId="1" SourceUrl="http://localhost:60598/Service1.svc?xsd=xsd1" />
    <MetadataFile FileName="Service12.xsd" MetadataType="Schema" ID="efb00b3e-f135-4456-9b3a-764db8815578" SourceId="1" SourceUrl="http://localhost:60598/Service1.svc?xsd=xsd2" />
  </Metadata>
  <Extensions>
    <ExtensionFile FileName="configuration91.svcinfo" Name="configuration91.svcinfo" />
    <ExtensionFile FileName="configuration.svcinfo" Name="configuration.svcinfo" />
  </Extensions>
</ReferenceGroup>